{
  "ReRoutes": [
    // Catalog API
    {
      "DownstreamPathTemplate": "/api/v1/Catalog",
      "DownstreamPathScheme": "http",
      "DownstreamPathHostAndPorts": [
        {
          "Host": "catalogapi",
          "Port": "80"
        }
      ],
      "UpstreamPathTemplate": "/Catalog",
      "UpstreamHttpMethod": [ "GET", "POST", "PUT" ]
    },
    {
      "DownstreamPathTemplate": "/api/v1/Catalog/{id}",
      "DownstreamPathScheme": "http",
      "DownstreamPathHostAndPorts": [
        {
          "Host": "catalogapi",
          "Port": "80"
        }
      ],
      "UpstreamPathTemplate": "/Catalog/{id}",
      "UpstreamHttpMethod": [ "GET", "DELETE" ]
    },
    {
      "DownstreamPathTemplate": "/api/v1/Catalog/GetProductByCategory/{category}",
      "DownstreamPathScheme": "http",
      "DownstreamPathHostAndPorts": [
        {
          "Host": "catalogapi",
          "Port": "80"
        }
      ],
      "UpstreamPathTemplate": "/Catalog/GetProductByCategory/{category}",
      "UpstreamHttpMethod": [ "GET" ]
    },
    // ShopCart API
    {
      "DownstreamPathTemplate": "/api/v1/ShopCart",
      "DownstreamPathScheme": "http",
      "DownstreamPathHostAndPorts": [
        {
          "Host": "shopcartapi",
          "Port": "80"
        }
      ],
      "UpstreamPathTemplate": "/ShopCart",
      "UpstreamHttpMethod": [ "GET", "POST" ]
    },
    {
      "DownstreamPathTemplate": "/api/v1/ShopCart/{userName}",
      "DownstreamPathScheme": "http",
      "DownstreamPathHostAndPorts": [
        {
          "Host": "shopcartapi",
          "Port": "80"
        }
      ],
      "UpstreamPathTemplate": "/ShopCart/{userName}",
      "UpstreamHttpMethod": [ "DELETE" ]
    },
    {
      "DownstreamPathTemplate": "/api/v1/ShopCart/Checkout",
      "DownstreamPathScheme": "http",
      "DownstreamPathHostAndPorts": [
        {
          "Host": "shopcartapi",
          "Port": "80"
        }
      ],
      "UpstreamPathTemplate": "/ShopCart/Checkout",
      "UpstreamHttpMethod": [ "POST" ]
    },
    // Order Api
    {
      "DownstreamPathTemplate": "/api/v1/Order",
      "DownstreamPathScheme": "http",
      "DownstreamPathHostAndPorts": [
        {
          "Host": "orderingapi",
          "Port": "80"
        }
      ],
      "UpstreamPathTemplate": "/Order",
      "UpstreamHttpMethod": [ "POST" ]
    }
  ]
}